__init__.py
panel_imputer.py
panel_imputer-0.8.2.dist-info/licenses/LICENSE
panel_imputer-0.8.2.dist-info/METADATA
panel_imputer-0.8.2.dist-info/WHEEL
panel_imputer-0.8.2.dist-info/top_level.txt
panel_imputer-0.8.2.dist-info/RECORD
