Metadata-Version: 2.4
Name: panel-imputer
Version: 0.8.2
Summary: A small sklearn compatible imputer for panel data.
Author-email: DaMitti <da.mitti@posteo.de>
License-Expression: MIT
Project-URL: Homepage, https://github.com/ccew-unibw/panel-imputer
Project-URL: Issues, https://github.com/ccew-unibw/panel-imputer/issues
Classifier: Programming Language :: Python :: 3
Classifier: Operating System :: OS Independent
Requires-Python: >=3.10
License-File: LICENSE
Requires-Dist: scikit-learn>=1.2
Requires-Dist: pandas>=2.0
Requires-Dist: numpy>=1.24
Requires-Dist: joblib>=1.1.1
Requires-Dist: tqdm>=4.65
Dynamic: license-file
